AkimFindLibrary/AkimFindLibrary.py
AkimFindLibrary/__init__.py
AkimFindLibrary-0.0.5.dist-info/METADATA
AkimFindLibrary-0.0.5.dist-info/WHEEL
AkimFindLibrary-0.0.5.dist-info/top_level.txt
AkimFindLibrary-0.0.5.dist-info/RECORD
