Metadata-Version: 2.1
Name: AkimFindLibrary
Version: 0.0.5
Summary: This is the simplest module for EGE Number 24.
Home-page: https://github.com/Akello1
Author: Akim_b
Author-email: akim.petbu@gmail.com
Project-URL: GitHub, https://github.com/Akello1
Keywords: file
Classifier: Programming Language :: Python :: 3.11
Classifier: License :: OSI Approved :: MIT License
Classifier: Operating System :: OS Independent
Requires-Python: >=3.6
Requires-Dist: requests >=2.24.1
